{"lat": 25.2653, "lon": 55.2925, "timezone": "Asia/Dubai", "timezone_offset": 14400, "current": {"dt": 1645387200, "sunrise": 1645411754, "sunset": 1645452964, "temp": 296.23, "feels_like": 296.16, "pressure": 1013, "humidity": 60, "dew_point": 288.05, "uvi": 0, "clouds": 0, "visibility": 10000, "wind_speed": 3.6, "wind_deg": 73, "wind_gust": 3.66, "weather": [{"id": 800, "main": "Clear", "description": "clear sky", "icon": "01n"}]}, "hourly": [{"dt": 1645315200, "temp": 297.98, "feels_like": 298.03, "pressure": 1012, "humidity": 58, "dew_point": 289.16, "uvi": 1.54, "clouds": 0, "visibility": 10000, "wind_speed": 5.24, "wind_deg": 307, "wind_gust": 5.83, "weather": [{"id": 800, "main": "Clear", "description": "clear sky", "icon": "01n"}]}, {"dt": 1645318800, "temp": 297.98, "feels_like": 298.03, "pressure": 1012, "humidity": 58, "dew_point": 289.16, "uvi": 1.54, "clouds": 0, "visibility": 10000, "wind_speed": 5.24, "wind_deg": 307, "wind_gust": 5.83, "weather": [{"id": 800, "main": "Clear", "description": "clear sky", "icon": "01n"}]}, {"dt": 1645322400, "temp": 297.98, "feels_like": 298.03, "pressure": 1012, "humidity": 58, "dew_point": 289.16, "uvi": 1.54, "clouds": 0, "visibility": 10000, "wind_speed": 5.24, "wind_deg": 307, "wind_gust": 5.83, "weather": [{"id": 800, "main": "Clear", "description": "clear sky", "icon": "01n"}]}, {"dt": 1645326000, "temp": 297.98, "feels_like": 298.03, "pressure": 1012, "humidity": 58, "dew_point": 289.16, "uvi": 1.54, "clouds": 0, "visibility": 10000, "wind_speed": 5.24, "wind_deg": 307, "wind_gust": 5.83, "weather": [{"id": 800, "main": "Clear", "description": "clear sky", "icon": "01d"}]}, {"dt": 1645329600, "temp": 297.98, "feels_like": 298.03, "pressure": 1012, "humidity": 58, "dew_point": 289.16, "uvi": 1.54, "clouds": 0, "visibility": 10000, "wind_speed": 5.24, "wind_deg": 307, "wind_gust": 5.83, "weather": [{"id": 800, "main": "Clear", "description": "clear sky", "icon": "01d"}]}, {"dt": 1645333200, "temp": 297.98, "feels_like": 298.03, "pressure": 1012, "humidity": 58, "dew_point": 289.16, "uvi": 1.54, "clouds": 0, "visibility": 10000, "wind_speed": 5.24, "wind_deg": 307, "wind_gust": 5.83, "weather": [{"id": 800, "main": "Clear", "description": "clear sky", "icon": "01d"}]}, {"dt": 1645336800, "temp": 297.98, "feels_like": 298.03, "pressure": 1012, "humidity": 58, "dew_point": 289.16, "uvi": 1.54, "clouds": 0, "visibility": 10000, "wind_speed": 5.24, "wind_deg": 307, "wind_gust": 5.83, "weather": [{"id": 800, "main": "Clear", "description": "clear sky", "icon": "01d"}]}, {"dt": 1645340400, "temp": 297.98, "feels_like": 298.03, "pressure": 1012, "humidity": 58, "dew_point": 289.16, "uvi": 1.54, "clouds": 0, "visibility": 10000, "wind_speed": 5.24, "wind_deg": 307, "wind_gust": 5.83, "weather": [{"id": 800, "main": "Clear", "description": "clear sky", "icon": "01d"}]}, {"dt": 1645344000, "temp": 297.98, "feels_like": 298.03, "pressure": 1012, "humidity": 58, "dew_point": 289.16, "uvi": 1.54, "clouds": 0, "visibility": 10000, "wind_speed": 5.24, "wind_deg": 307, "wind_gust": 5.83, "weather": [{"id": 800, "main": "Clear", "description": "clear sky", "icon": "01d"}]}, {"dt": 1645347600, "temp": 297.98, "feels_like": 298.03, "pressure": 1012, "humidity": 58, "dew_point": 289.16, "uvi": 1.54, "clouds": 0, "visibility": 10000, "wind_speed": 5.24, "wind_deg": 307, "wind_gust": 5.83, "weather": [{"id": 800, "main": "Clear", "description": "clear sky", "icon": "01d"}]}, {"dt": 1645351200, "temp": 297.98, "feels_like": 298.03, "pressure": 1012, "humidity": 58, "dew_point": 289.16, "uvi": 1.54, "clouds": 0, "visibility": 10000, "wind_speed": 5.24, "wind_deg": 307, "wind_gust": 5.83, "weather": [{"id": 800, "main": "Clear", "description": "clear sky", "icon": "01d"}]}, {"dt": 1645354800, "temp": 297.98, "feels_like": 298.03, "pressure": 1012, "humidity": 58, "dew_point": 289.16, "uvi": 1.54, "clouds": 0, "visibility": 10000, "wind_speed": 5.24, "wind_deg": 307, "wind_gust": 5.83, "weather": [{"id": 800, "main": "Clear", "description": "clear sky", "icon": "01d"}]}, {"dt": 1645358400, "temp": 297.98, "feels_like": 298.03, "pressure": 1012, "humidity": 58, "dew_point": 289.16, "uvi": 1.54, "clouds": 0, "visibility": 10000, "wind_speed": 5.24, "wind_deg": 307, "wind_gust": 5.83, "weather": [{"id": 800, "main": "Clear", "description": "clear sky", "icon": "01d"}]}, {"dt": 1645362000, "temp": 297.63, "feels_like": 297.7, "pressure": 1012, "humidity": 60, "dew_point": 289.36, "uvi": 0.41, "clouds": 0, "visibility": 10000, "wind_speed": 4.15, "wind_deg": 318, "wind_gust": 4.6, "weather": [{"id": 800, "main": "Clear", "description": "clear sky", "icon": "01d"}]}, {"dt": 1645365600, "temp": 297.18, "feels_like": 297.28, "pressure": 1012, "humidity": 63, "dew_point": 289.71, "uvi": 0, "clouds": 0, "visibility": 10000, "wind_speed": 3.36, "wind_deg": 332, "wind_gust": 3.53, "weather": [{"id": 800, "main": "Clear", "description": "clear sky", "icon": "01d"}]}, {"dt": 1645369200, "temp": 296.89, "feels_like": 296.99, "pressure": 1013, "humidity": 64, "dew_point": 289.68, "uvi": 0, "clouds": 0, "visibility": 10000, "wind_speed": 3.25, "wind_deg": 358, "wind_gust": 3.42, "weather": [{"id": 800, "main": "Clear", "description": "clear sky", "icon": "01n"}]}, {"dt": 1645372800, "temp": 296.7, "feels_like": 296.76, "pressure": 1013, "humidity": 63, "dew_point": 289.25, "uvi": 0, "clouds": 0, "visibility": 10000, "wind_speed": 3.46, "wind_deg": 28, "wind_gust": 3.64, "weather": [{"id": 800, "main": "Clear", "description": "clear sky", "icon": "01n"}]}, {"dt": 1645376400, "temp": 296.6, "feels_like": 296.65, "pressure": 1014, "humidity": 63, "dew_point": 289.16, "uvi": 0, "clouds": 0, "visibility": 10000, "wind_speed": 3.91, "wind_deg": 33, "wind_gust": 4.41, "weather": [{"id": 800, "main": "Clear", "description": "clear sky", "icon": "01n"}]}, {"dt": 1645380000, "temp": 296.58, "feels_like": 296.57, "pressure": 1014, "humidity": 61, "dew_point": 288.64, "uvi": 0, "clouds": 0, "visibility": 10000, "wind_speed": 3.66, "wind_deg": 44, "wind_gust": 3.85, "weather": [{"id": 800, "main": "Clear", "description": "clear sky", "icon": "01n"}]}, {"dt": 1645383600, "temp": 296.38, "feels_like": 296.35, "pressure": 1013, "humidity": 61, "dew_point": 288.45, "uvi": 0, "clouds": 0, "visibility": 10000, "wind_speed": 3.79, "wind_deg": 56, "wind_gust": 4, "weather": [{"id": 800, "main": "Clear", "description": "clear sky", "icon": "01n"}]}, {"dt": 1645387200, "temp": 296.23, "feels_like": 296.16, "pressure": 1013, "humidity": 60, "dew_point": 288.05, "uvi": 0, "clouds": 0, "visibility": 10000, "wind_speed": 3.6, "wind_deg": 73, "wind_gust": 3.66, "weather": [{"id": 800, "main": "Clear", "description": "clear sky", "icon": "01n"}]}, {"dt": 1645390800, "temp": 295.89, "feels_like": 295.29, "pressure": 1012, "humidity": 41, "dew_point": 281.97, "uvi": 0, "clouds": 0, "visibility": 10000, "wind_speed": 3.6, "wind_deg": 120, "weather": [{"id": 800, "main": "Clear", "description": "clear sky", "icon": "01n"}]}, {"dt": 1645394400, "temp": 294.54, "feels_like": 293.94, "pressure": 1012, "humidity": 46, "dew_point": 282.46, "uvi": 0, "clouds": 0, "visibility": 10000, "wind_speed": 2.06, "wind_deg": 140, "weather": [{"id": 800, "main": "Clear", "description": "clear sky", "icon": "01n"}]}, {"dt": 1645398000, "temp": 294.79, "feels_like": 294.29, "pressure": 1011, "humidity": 49, "dew_point": 283.63, "uvi": 0, "clouds": 0, "visibility": 10000, "wind_speed": 1.54, "wind_deg": 210, "weather": [{"id": 800, "main": "Clear", "description": "clear sky", "icon": "01n"}]}]}